{"nodes": [{"id": "projects_ativos_n8n_mcp_create_workflows_py", "label": "create_workflows.py", "file_type": "code", "source_file": "Projects\\Ativos\\n8n-mcp\\create_workflows.py", "source_location": "L1"}, {"id": "create_workflows_uid", "label": "uid()", "file_type": "code", "source_file": "Projects\\Ativos\\n8n-mcp\\create_workflows.py", "source_location": "L18"}, {"id": "create_workflows_create_workflow", "label": "create_workflow()", "file_type": "code", "source_file": "Projects\\Ativos\\n8n-mcp\\create_workflows.py", "source_location": "L22"}, {"id": "create_workflows_workflow_tb1_price_alert", "label": "workflow_tb1_price_alert()", "file_type": "code", "source_file": "Projects\\Ativos\\n8n-mcp\\create_workflows.py", "source_location": "L36"}, {"id": "create_workflows_workflow_fat1_invoice_scanner", "label": "workflow_fat1_invoice_scanner()", "file_type": "code", "source_file": "Projects\\Ativos\\n8n-mcp\\create_workflows.py", "source_location": "L204"}, {"id": "create_workflows_workflow_tb2_daily_pnl", "label": "workflow_tb2_daily_pnl()", "file_type": "code", "source_file": "Projects\\Ativos\\n8n-mcp\\create_workflows.py", "source_location": "L326"}, {"id": "create_workflows_rationale_1", "label": "create_workflows.py \u2014 Cria os workflows iniciais no n8n via API REST Correr: pyt", "file_type": "rationale", "source_file": "Projects\\Ativos\\n8n-mcp\\create_workflows.py", "source_location": "L1"}], "edges": [{"source": "projects_ativos_n8n_mcp_create_workflows_py", "target": "json", "relation": "imports", "confidence": "EXTRACTED", "source_file": "Projects\\Ativos\\n8n-mcp\\create_workflows.py", "source_location": "L6", "weight": 1.0}, {"source": "projects_ativos_n8n_mcp_create_workflows_py", "target": "httpx", "relation": "imports", "confidence": "EXTRACTED", "source_file": "Projects\\Ativos\\n8n-mcp\\create_workflows.py", "source_location": "L7", "weight": 1.0}, {"source": "projects_ativos_n8n_mcp_create_workflows_py", "target": "uuid", "relation": "imports", "confidence": "EXTRACTED", "source_file": "Projects\\Ativos\\n8n-mcp\\create_workflows.py", "source_location": "L8", "weight": 1.0}, {"source": "projects_ativos_n8n_mcp_create_workflows_py", "target": "create_workflows_uid", "relation": "contains", "confidence": "EXTRACTED", "source_file": "Projects\\Ativos\\n8n-mcp\\create_workflows.py", "source_location": "L18", "weight": 1.0}, {"source": "projects_ativos_n8n_mcp_create_workflows_py", "target": "create_workflows_create_workflow", "relation": "contains", "confidence": "EXTRACTED", "source_file": "Projects\\Ativos\\n8n-mcp\\create_workflows.py", "source_location": "L22", "weight": 1.0}, {"source": "projects_ativos_n8n_mcp_create_workflows_py", "target": "create_workflows_workflow_tb1_price_alert", "relation": "contains", "confidence": "EXTRACTED", "source_file": "Projects\\Ativos\\n8n-mcp\\create_workflows.py", "source_location": "L36", "weight": 1.0}, {"source": "projects_ativos_n8n_mcp_create_workflows_py", "target": "create_workflows_workflow_fat1_invoice_scanner", "relation": "contains", "confidence": "EXTRACTED", "source_file": "Projects\\Ativos\\n8n-mcp\\create_workflows.py", "source_location": "L204", "weight": 1.0}, {"source": "projects_ativos_n8n_mcp_create_workflows_py", "target": "create_workflows_workflow_tb2_daily_pnl", "relation": "contains", "confidence": "EXTRACTED", "source_file": "Projects\\Ativos\\n8n-mcp\\create_workflows.py", "source_location": "L326", "weight": 1.0}, {"source": "create_workflows_workflow_tb1_price_alert", "target": "create_workflows_uid", "relation": "calls", "confidence": "EXTRACTED", "source_file": "Projects\\Ativos\\n8n-mcp\\create_workflows.py", "source_location": "L37", "weight": 1.0}, {"source": "create_workflows_workflow_fat1_invoice_scanner", "target": "create_workflows_uid", "relation": "calls", "confidence": "EXTRACTED", "source_file": "Projects\\Ativos\\n8n-mcp\\create_workflows.py", "source_location": "L205", "weight": 1.0}, {"source": "create_workflows_workflow_tb2_daily_pnl", "target": "create_workflows_uid", "relation": "calls", "confidence": "EXTRACTED", "source_file": "Projects\\Ativos\\n8n-mcp\\create_workflows.py", "source_location": "L327", "weight": 1.0}, {"source": "create_workflows_rationale_1", "target": "projects_ativos_n8n_mcp_create_workflows_py", "relation": "rationale_for", "confidence": "EXTRACTED", "source_file": "Projects\\Ativos\\n8n-mcp\\create_workflows.py", "source_location": "L1", "weight": 1.0}], "raw_calls": [{"caller_nid": "create_workflows_uid", "callee": "str", "source_file": "Projects\\Ativos\\n8n-mcp\\create_workflows.py", "source_location": "L19"}, {"caller_nid": "create_workflows_uid", "callee": "uuid4", "source_file": "Projects\\Ativos\\n8n-mcp\\create_workflows.py", "source_location": "L19"}, {"caller_nid": "create_workflows_create_workflow", "callee": "post", "source_file": "Projects\\Ativos\\n8n-mcp\\create_workflows.py", "source_location": "L23"}, {"caller_nid": "create_workflows_create_workflow", "callee": "raise_for_status", "source_file": "Projects\\Ativos\\n8n-mcp\\create_workflows.py", "source_location": "L24"}, {"caller_nid": "create_workflows_create_workflow", "callee": "json", "source_file": "Projects\\Ativos\\n8n-mcp\\create_workflows.py", "source_location": "L25"}, {"caller_nid": "create_workflows_create_workflow", "callee": "patch", "source_file": "Projects\\Ativos\\n8n-mcp\\create_workflows.py", "source_location": "L28"}]}